leab/__init__.py
leab-0.1.11.dist-info/licenses/LICENSE
leab-0.1.11.dist-info/METADATA
leab-0.1.11.dist-info/WHEEL
leab-0.1.11.dist-info/top_level.txt
leab-0.1.11.dist-info/RECORD
