Metadata-Version: 2.4
Name: leab
Version: 0.1.11
Summary: Add your description here
Project-URL: Repository, https://github.com/tlentali/leab
Project-URL: Documentation, https://tlentali.github.io/leab/
Requires-Python: >=3.12
License-File: LICENSE
Requires-Dist: numpy>=2.2.4
Requires-Dist: pandas>=2.2.3
Requires-Dist: scipy>=1.15.2
Requires-Dist: statsmodels>=0.14.4
Dynamic: license-file
